ccnmtldjango/__init__.py
ccnmtldjango/template/.gitignore
ccnmtldjango/template/Dockerfile_tmpl
ccnmtldjango/template/Makefile_tmpl
ccnmtldjango/template/django.mk
ccnmtldjango/template/docker-compose.yml_tmpl
ccnmtldjango/template/docker-run.sh
ccnmtldjango/template/docker.mk
ccnmtldjango/template/eslintrc.js
ccnmtldjango/template/js.mk
ccnmtldjango/template/make.mk
ccnmtldjango/template/manage.py_tmpl
ccnmtldjango/template/package.json_tmpl
ccnmtldjango/template/requirements.txt
ccnmtldjango/template/virtualenv.py
ccnmtldjango/template/+package+/__init__.py
ccnmtldjango/template/+package+/s3utils.py
ccnmtldjango/template/+package+/settings.py_tmpl
ccnmtldjango/template/+package+/settings_compose.py
ccnmtldjango/template/+package+/settings_docker.py
ccnmtldjango/template/+package+/settings_production.py_tmpl
ccnmtldjango/template/+package+/settings_shared.py_tmpl
ccnmtldjango/template/+package+/settings_staging.py_tmpl
ccnmtldjango/template/+package+/urls.py_tmpl
ccnmtldjango/template/+package+/wsgi.py_tmpl
ccnmtldjango/template/+package+/main/__init__.py
ccnmtldjango/template/+package+/main/models.py
ccnmtldjango/template/+package+/main/smoke.py
ccnmtldjango/template/+package+/main/views.py
ccnmtldjango/template/+package+/main/tests/__init__.py
ccnmtldjango/template/+package+/main/tests/test_models.py
ccnmtldjango/template/+package+/main/tests/test_views.py
ccnmtldjango/template/+package+/templates/404.html
ccnmtldjango/template/+package+/templates/500.html
ccnmtldjango/template/+package+/templates/base.html_tmpl
ccnmtldjango/template/+package+/templates/stats.html_tmpl
ccnmtldjango/template/+package+/templates/admin/login.html
ccnmtldjango/template/+package+/templates/flatpages/default.html
ccnmtldjango/template/+package+/templates/impersonate/list_users.html
ccnmtldjango/template/+package+/templates/infranil/index.html
ccnmtldjango/template/+package+/templates/main/index.html
ccnmtldjango-1.11.0.dist-info/DESCRIPTION.rst
ccnmtldjango-1.11.0.dist-info/METADATA
ccnmtldjango-1.11.0.dist-info/RECORD
ccnmtldjango-1.11.0.dist-info/WHEEL
ccnmtldjango-1.11.0.dist-info/entry_points.txt
ccnmtldjango-1.11.0.dist-info/metadata.json
ccnmtldjango-1.11.0.dist-info/top_level.txt
