Metadata-Version: 2.0
Name: ccnmtldjango
Version: 1.11.0
Summary: Paste template for Django development at CCNMTL
Home-page: https://github.com/ccnmtl/ccnmtldjango/
Author: Anders Pearson
Author-email: ccnmtl-dev@columbia.edu
License: UNKNOWN
Platform: UNKNOWN
Requires-Dist: PasteScript
